liber/__init__.py
liber/core.py
liber-1.0.1.dist-info/LICENSE
liber-1.0.1.dist-info/METADATA
liber-1.0.1.dist-info/WHEEL
liber-1.0.1.dist-info/top_level.txt
liber-1.0.1.dist-info/RECORD
